magfa/__init__.py
magfa/error_codes.py
magfa/klass.py
magfa/logger.py
magfa/http_utils/__init__.py
magfa/http_utils/klass.py
magfa/http_utils/status_codes.py
magfa-1.0.0.dist-info/licenses/LICENSE
magfa-1.0.0.dist-info/METADATA
magfa-1.0.0.dist-info/WHEEL
magfa-1.0.0.dist-info/top_level.txt
magfa-1.0.0.dist-info/RECORD
