Metadata-Version: 2.4
Name: magfa
Version: 1.0.0
Summary: magfa-client is a python client library for interacting with magfa SMS webservice v2.
Author-email: Ali Sharify <alisharifyofficial@gmail.com>
License-Expression: GPL-3.0
Project-URL: Homepage, https://github.com/alisharify7/magfa-client
Project-URL: Documentation, https://github.com/alisharify7/magfa-client
Project-URL: Repository, https://github.com/alisharify7/magfa-client
Project-URL: Donate, https://www.coffeete.ir/alisharify7
Project-URL: Source, https://github.com/alisharify7/magfa-client
Keywords: sms,magfa,messaging,api,client,magfa-client,magfa-py,magfa-python
Classifier: Development Status :: 3 - Alpha
Classifier: Intended Audience :: Developers
Classifier: Topic :: Communications :: Telephony
Classifier: Programming Language :: Python :: 3
Classifier: Programming Language :: Python :: 3.9
Classifier: Programming Language :: Python :: 3.10
Requires-Python: >=3.9
License-File: LICENSE
Requires-Dist: requests>=2.32.3
Requires-Dist: python-dotenv>=1.1.0
Dynamic: license-file
